Metadata-Version: 2.1
Name: wanted-models
Version: 0.0.7
Summary: Wanted models
Home-page: https://gitlab.argus360.kz/argus/kgp/wanted-models/
Author: mercurial
Author-email: dias.nespayev@gmail.com
License: MIT
Requires-Python: >=3.8
